sphinx_gha/__init__.py
sphinx_gha/action.py
sphinx_gha/common.py
sphinx_gha/ext.py
sphinx_gha/git_ref.py
sphinx_gha/workflow.py
sphinx_gha-1.0.0.dist-info/licenses/LICENSE.md
sphinx_gha-1.0.0.dist-info/METADATA
sphinx_gha-1.0.0.dist-info/WHEEL
sphinx_gha-1.0.0.dist-info/top_level.txt
sphinx_gha-1.0.0.dist-info/RECORD
